torchcvnn/__init__.py
torchcvnn/datasets/__init__.py
torchcvnn/datasets/miccai2023.py
torchcvnn/datasets/polsf.py
torchcvnn/datasets/s1slc.py
torchcvnn/datasets/alos2/__init__.py
torchcvnn/datasets/alos2/dataset.py
torchcvnn/datasets/alos2/leader_file.py
torchcvnn/datasets/alos2/parse_utils.py
torchcvnn/datasets/alos2/sar_image.py
torchcvnn/datasets/alos2/trailer_file.py
torchcvnn/datasets/alos2/vol_file.py
torchcvnn/datasets/atrnet_star/__init__.py
torchcvnn/datasets/atrnet_star/dataset.py
torchcvnn/datasets/atrnet_star/download.py
torchcvnn/datasets/atrnet_star/parse_xml.py
torchcvnn/datasets/bretigny/__init__.py
torchcvnn/datasets/bretigny/dataset.py
torchcvnn/datasets/mstar/__init__.py
torchcvnn/datasets/mstar/dataset.py
torchcvnn/datasets/sample/__init__.py
torchcvnn/datasets/sample/dataset.py
torchcvnn/datasets/sample/download_filelist.py
torchcvnn/datasets/sample/filelist.py
torchcvnn/datasets/slc/__init__.py
torchcvnn/datasets/slc/ann_file.py
torchcvnn/datasets/slc/dataset.py
torchcvnn/datasets/slc/slc_file.py
torchcvnn/models/__init__.py
torchcvnn/models/vision_transformer.py
torchcvnn/nn/__init__.py
torchcvnn/nn/functional.py
torchcvnn/nn/modules/__init__.py
torchcvnn/nn/modules/activation.py
torchcvnn/nn/modules/batchnorm.py
torchcvnn/nn/modules/conv.py
torchcvnn/nn/modules/dropout.py
torchcvnn/nn/modules/initialization.py
torchcvnn/nn/modules/loss.py
torchcvnn/nn/modules/normalization.py
torchcvnn/nn/modules/pooling.py
torchcvnn/nn/modules/transformer.py
torchcvnn/nn/modules/upsampling.py
torchcvnn/nn/modules/vit.py
torchcvnn/transforms/__init__.py
torchcvnn/transforms/functional.py
torchcvnn/transforms/transforms.py
torchcvnn-0.9.8.dist-info/licenses/LICENSE
torchcvnn-0.9.8.dist-info/METADATA
torchcvnn-0.9.8.dist-info/WHEEL
torchcvnn-0.9.8.dist-info/top_level.txt
torchcvnn-0.9.8.dist-info/RECORD
