Metadata-Version: 2.4
Name: torchcvnn
Version: 0.9.8
Summary: torchcvnn provides complex valued layers to be used with pytorch
Author-email: Jeremy Fix <jeremy.fix@centralesupelec.fr>, Quentin Gabot <quentin.gabot@centralesupelec.fr>
Maintainer-email: Jeremy Fix <jeremy.fix@centralesupelec.fr>
Keywords: deep learning,pytorch,complex valued neural networks
Classifier: Development Status :: 4 - Beta
Classifier: Programming Language :: Python
Requires-Python: >=3.9.10
License-File: LICENSE
Requires-Dist: torch>=2.0
Requires-Dist: numpy>=2.0
Requires-Dist: requests>=2.31.0
Requires-Dist: tqdm>=4.66.1
Requires-Dist: pillow>=11.1.0
Requires-Dist: scipy>=1.6.0
Requires-Dist: h5py>=3.12.1
Requires-Dist: huggingface-hub>=0.32.6
Provides-Extra: docs
Requires-Dist: sphinx>=8.1.3; extra == "docs"
Requires-Dist: furo>=2024.04.27; extra == "docs"
Requires-Dist: sphinx-copybutton>=0.5.2; extra == "docs"
Dynamic: license-file
